ludic_slides/__init__.py
ludic_slides/cli.py
ludic_slides/components.py
ludic_slides/themes.py
ludic_slides-0.0.1.dist-info/METADATA
ludic_slides-0.0.1.dist-info/WHEEL
ludic_slides-0.0.1.dist-info/entry_points.txt
ludic_slides-0.0.1.dist-info/licenses/LICENCE
ludic_slides-0.0.1.dist-info/RECORD
