Metadata-Version: 2.4
Name: ludic-slides
Version: 0.0.1
Summary: Build fast presentations with Ludic
Author-email: Pavel Dedík <dedikx@gmail.com>
Maintainer-email: Pavel Dedík <dedikx@gmail.com>
License-Expression: MIT
License-File: LICENCE
Keywords: html,presentation,slides
Classifier: Development Status :: 5 - Production/Stable
Classifier: Intended Audience :: Education
Classifier: Intended Audience :: Other Audience
Classifier: License :: OSI Approved :: MIT License
Classifier: Operating System :: OS Independent
Classifier: Programming Language :: Python :: 3 :: Only
Classifier: Programming Language :: Python :: 3.12
Classifier: Programming Language :: Python :: 3.13
Classifier: Programming Language :: Python :: Implementation :: CPython
Classifier: Topic :: Multimedia :: Graphics :: Presentation
Requires-Python: >=3.12
Requires-Dist: ludic>=0.5.5
Requires-Dist: pygments
Provides-Extra: test
Requires-Dist: pytest; extra == 'test'
Requires-Dist: pytest-cov; extra == 'test'
